RUNNER.py
deploymentenv.py
fork-pycor.py
pycor.py
pycor2.py
snake-game.py
other/filecreate.py
src/pycor/__init__.py
src/pycor/pycor.py
templates/turtletemp.py
pycorapp-0.1.0.dist-info/METADATA
pycorapp-0.1.0.dist-info/WHEEL
pycorapp-0.1.0.dist-info/licenses/LICENSE
pycorapp-0.1.0.dist-info/RECORD
