Metadata-Version: 2.1
Name: pycorapp
Version: 0.1.0
Summary: The official PyPi python package!
Project-URL: Homepage, https://github.com/UnknownUser2222/pycor
Author-email: UnknownUser2222 <userunamed981@gmail.com>
License-File: LICENSE
Classifier: License :: OSI Approved :: MIT License
Classifier: Operating System :: OS Independent
Classifier: Programming Language :: Python :: 3
Requires-Python: >=3.10
